timeseries_agent/__init__.py
timeseries_agent/data/__init__.py
timeseries_agent/data/rl_sequence_dataset.py
timeseries_agent/data/sample_data.py
timeseries_agent/models/__init__.py
timeseries_agent/models/policy_gradient_agent.py
timeseries_agent/tuning/__init__.py
timeseries_agent/tuning/genetic.py
timeseries_agent/tuning/tuner.py
timeseries_agent/utils/__init__.py
timeseries_agent/utils/rl_utils.py
timeseries_agent/utils/visualization.py
timeseries_agent-0.0.29.dist-info/licenses/LICENSE
timeseries_agent-0.0.29.dist-info/METADATA
timeseries_agent-0.0.29.dist-info/WHEEL
timeseries_agent-0.0.29.dist-info/top_level.txt
timeseries_agent-0.0.29.dist-info/RECORD
