Metadata-Version: 2.4
Name: timeseries_agent
Version: 0.0.29
Summary: A Policy Gradient RL agent for time series prediction using PyTorch Lightning.
Home-page: https://github.com/cpohagwu/timeseries_agent
Author: Collins Patrick Ohagwu
Author-email: Collins Patrick Ohagwu <cpohagwu@gmail.com>
License-Expression: Apache-2.0
Project-URL: Homepage, https://github.com/cpohagwu/timeseries_agent
Project-URL: Bug Tracker, https://github.com/cpohagwu/timeseries_agent/issues
Project-URL: Documentation, https://timeseries_agent.readthedocs.io/en/latest/
Classifier: Programming Language :: Python :: 3
Classifier: Operating System :: Microsoft :: Windows
Classifier: Operating System :: POSIX :: Linux
Classifier: Operating System :: MacOS
Requires-Python: >=3.8
License-File: LICENSE
Requires-Dist: pandas>=1.0.0
Requires-Dist: numpy>=1.19.0
Requires-Dist: lightning>=2.5.0
Requires-Dist: matplotlib>=3.0.0
Requires-Dist: torch>=1.9.0; platform_system == "Linux"
Requires-Dist: torch>=1.9.0; platform_system == "Darwin"
Requires-Dist: torch>=1.9.0; platform_system == "Windows"
Requires-Dist: scikit-learn>=1.6.1
Dynamic: author
Dynamic: home-page
Dynamic: license-file
Dynamic: requires-python
